{"name":"山河傳說","latest":"2022-06-18","pages":[{"broadcast_date":"2019-08-10","title":"#1 廬山","episodes":1,"podcasts":[{"caption":"(1) 秦始皇趕山 / 牯牛嶺","url":"https://podcasts.rthk.hk/podcast/media/taleoftheland/1622_1908081025_10155.mp3"}]},{"broadcast_date":"2019-08-17","title":"#2 廬山","episodes":1,"podcasts":[{"caption":"(2) 竹林隱寺 / 月照松林","url":"https://podcasts.rthk.hk/podcast/media/taleoftheland/1622_1908081025_65313.mp3"}]},{"broadcast_date":"2019-08-24","title":"#3 廬山","episodes":1,"podcasts":[{"caption":"(3) 仙人洞 / 乾隆皇帝遊廬山","url":"https://podcasts.rthk.hk/podcast/media/taleoftheland/1622_1908141228_51365.mp3"}]},{"broadcast_date":"2019-08-31","title":"#4 廬山","episodes":1,"podcasts":[{"caption":"(4) 五老峰 / 姊妹峰","url":"https://podcasts.rthk.hk/podcast/media/taleoftheland/1622_1908141228_34023.mp3"}]},{"broadcast_date":"2019-09-07","title":"#5 廬山","episodes":1,"podcasts":[{"caption":"(5) 蘇東坡「西李碑」","url":"https://podcasts.rthk.hk/podcast/media/taleoftheland/1622_1909051345_50693.mp3"}]},{"broadcast_date":"2019-09-14","title":"#06 廬山","episodes":1,"podcasts":[{"caption":"(6) 陶淵明掛印辭鄉","url":"https://podcasts.rthk.hk/podcast/media/taleoftheland/1622_1909051345_53074.mp3"}]},{"broadcast_date":"2019-09-21","title":"#07 廬山","episodes":1,"podcasts":[{"caption":"(7) 御碑亭 / 廬山三峽橋圖 / 觀音橋","url":"https://podcasts.rthk.hk/podcast/media/taleoftheland/1622_1909192312_63540.mp3"}]},{"broadcast_date":"2019-09-28","title":"#08 廬山","episodes":1,"podcasts":[{"caption":"(8) 杏林 / 金星宋硯 / 雲霧茶","url":"https://podcasts.rthk.hk/podcast/media/taleoftheland/1622_1909192312_72894.mp3"}]},{"broadcast_date":"2019-10-05","title":"#9 長江三峽","episodes":1,"podcasts":[{"caption":"(1) 奉節","url":"https://podcasts.rthk.hk/podcast/media/taleoftheland/1622_1909261537_28836.mp3"}]},{"broadcast_date":"2019-10-12","title":"#10 長江三峽","episodes":1,"podcasts":[{"caption":"(2) 八陣圖","url":"https://podcasts.rthk.hk/podcast/media/taleoftheland/1622_1910081130_87440.mp3"}]},{"broadcast_date":"2019-10-19","title":"#11 長江三峽","episodes":1,"podcasts":[{"caption":"(3) 師徒修橋/ 灔灝堆","url":"https://podcasts.rthk.hk/podcast/media/taleoftheland/1622_1910190103_60478.mp3"}]},{"broadcast_date":"2019-10-26","title":"#12 長江三峽","episodes":1,"podcasts":[{"caption":"(4) 神女峰","url":"https://podcasts.rthk.hk/podcast/media/taleoftheland/1622_1910190105_95361.mp3"}]},{"broadcast_date":"2019-11-02","title":"#13 長江三峽","episodes":1,"podcasts":[{"caption":"(5) 巴東","url":"https://podcasts.rthk.hk/podcast/media/taleoftheland/1622_1911020233_35889.mp3"}]},{"broadcast_date":"2019-11-09","title":"#14 長江三峽","episodes":1,"podcasts":[{"caption":"(6) 屈原 (上)","url":"https://podcasts.rthk.hk/podcast/media/taleoftheland/1622_1911020233_15898.mp3"}]},{"broadcast_date":"2019-11-16","title":"#15 長江三峽","episodes":1,"podcasts":[{"caption":"(7) 屈原 (下)","url":"https://podcasts.rthk.hk/podcast/media/taleoftheland/1622_1911161637_43654.mp3"}]},{"broadcast_date":"2019-11-23","title":"長江三峽","episodes":1,"podcasts":[{"caption":"(8) 王昭君 (上)","url":"https://podcasts.rthk.hk/podcast/media/taleoftheland/1622_1911161637_96441.mp3"}]},{"broadcast_date":"2019-11-30","title":"#17 長江三峽","episodes":1,"podcasts":[{"caption":"(9) 王昭君 (下)","url":"https://podcasts.rthk.hk/podcast/media/taleoftheland/1622_1912071734_69358.mp3"}]},{"broadcast_date":"2019-12-07","title":"#18 長江三峽","episodes":1,"podcasts":[{"caption":"(10) 奇石","url":"https://podcasts.rthk.hk/podcast/media/taleoftheland/1622_1912071736_61963.mp3"}]},{"broadcast_date":"2019-12-14","title":"#19 長江三峽","episodes":1,"podcasts":[{"caption":"(11) 詩與水","url":"https://podcasts.rthk.hk/podcast/media/taleoftheland/1622_1912162008_35623.mp3"}]},{"broadcast_date":"2019-12-21","title":"#20 長江三峽","episodes":1,"podcasts":[{"caption":"(12) 張飛廟","url":"https://podcasts.rthk.hk/podcast/media/taleoftheland/1622_1912252009_82103.mp3"}]},{"broadcast_date":"2019-12-28","title":"#21 長江三峽","episodes":1,"podcasts":[{"caption":"(13) 玉泉塔/ 天然塔","url":"https://podcasts.rthk.hk/podcast/media/taleoftheland/1622_1912252008_37267.mp3"}]},{"broadcast_date":"2020-01-04","title":"#22 長江三峽","episodes":1,"podcasts":[{"caption":"(14) 巫山雲雨 / 箭穿峽","url":"https://podcasts.rthk.hk/podcast/media/taleoftheland/1622_2001031544_95175.mp3"}]},{"broadcast_date":"2020-01-11","title":"#23 杭州","episodes":1,"podcasts":[{"caption":"(1)","url":"https://podcasts.rthk.hk/podcast/media/taleoftheland/1622_2001101707_38490.mp3"}]},{"broadcast_date":"2020-01-18","title":"#24 杭州","episodes":1,"podcasts":[{"caption":"(2)","url":"https://podcasts.rthk.hk/podcast/media/taleoftheland/1622_2001101707_17766.mp3"}]},{"broadcast_date":"2020-01-25","title":"#25 杭州","episodes":1,"podcasts":[{"caption":"(3)","url":"https://podcasts.rthk.hk/podcast/media/taleoftheland/1622_2001311625_35263.mp3"}]},{"broadcast_date":"2020-02-01","title":"#26 杭州","episodes":1,"podcasts":[{"caption":"(4)","url":"https://podcasts.rthk.hk/podcast/media/taleoftheland/1622_2001311625_95492.mp3"}]},{"broadcast_date":"2020-02-08","title":"#27 杭州","episodes":1,"podcasts":[{"caption":"(5) 靈隱寺","url":"https://podcasts.rthk.hk/podcast/media/taleoftheland/1622_2002071824_17662.mp3"}]},{"broadcast_date":"2020-02-15","title":"#28 杭州","episodes":1,"podcasts":[{"caption":"(6) 岳墳","url":"https://podcasts.rthk.hk/podcast/media/taleoftheland/1622_2002071824_16143.mp3"}]},{"broadcast_date":"2020-02-22","title":"#29 杭州","episodes":1,"podcasts":[{"caption":"(7) 白堤","url":"https://podcasts.rthk.hk/podcast/media/taleoftheland/1622_2002211018_76533.mp3"}]},{"broadcast_date":"2020-02-29","title":"#30 杭州","episodes":1,"podcasts":[{"caption":"(8) 蘇堤春曉","url":"https://podcasts.rthk.hk/podcast/media/taleoftheland/1622_2002282022_68850.mp3"}]},{"broadcast_date":"2020-03-07","title":"#31 杭州","episodes":1,"podcasts":[{"caption":"(9) 一株楊柳一株桃","url":"https://podcasts.rthk.hk/podcast/media/taleoftheland/1622_2003061544_27425.mp3"}]},{"broadcast_date":"2020-03-14","title":"#32 杭州","episodes":1,"podcasts":[{"caption":"(10) 龍井茶葉虎跑水","url":"https://podcasts.rthk.hk/podcast/media/taleoftheland/1622_2003061544_92402.mp3"}]},{"broadcast_date":"2020-03-21","title":"#33 杭州","episodes":1,"podcasts":[{"caption":"(11) 梅妻鶴子鹿家人","url":"https://podcasts.rthk.hk/podcast/media/taleoftheland/1622_2003061544_27925.mp3"}]},{"broadcast_date":"2020-03-28","title":"#34 杭州","episodes":1,"podcasts":[{"caption":"(12) 錢江潮","url":"https://podcasts.rthk.hk/podcast/media/taleoftheland/1622_2003061544_15506.mp3"}]},{"broadcast_date":"2020-04-04","title":"#35 杭州","episodes":1,"podcasts":[{"caption":"(13) 吳山","url":"https://podcasts.rthk.hk/podcast/media/taleoftheland/1622_2004031450_28929.mp3"}]},{"broadcast_date":"2020-04-11","title":"#36 杭州","episodes":1,"podcasts":[{"caption":"(14) 寶俶塔與雷峰塔","url":"https://podcasts.rthk.hk/podcast/media/taleoftheland/1622_2004031450_49416.mp3"}]},{"broadcast_date":"2020-04-18","title":"#37 南京","episodes":1,"podcasts":[{"caption":"(1) 玄武湖 (上)","url":"https://podcasts.rthk.hk/podcast/media/taleoftheland/1622_2004031450_69240.mp3"}]},{"broadcast_date":"2020-04-25","title":"#38 南京","episodes":1,"podcasts":[{"caption":"(2) 玄武湖 (下)","url":"https://podcasts.rthk.hk/podcast/media/taleoftheland/1622_2004231657_56943.mp3"}]},{"broadcast_date":"2020-05-02","title":"#39 南京","episodes":1,"podcasts":[{"caption":"(3) 莫愁湖","url":"https://podcasts.rthk.hk/podcast/media/taleoftheland/1622_2004231657_99345.mp3"}]},{"broadcast_date":"2020-05-09","title":"#40 南京","episodes":1,"podcasts":[{"caption":"(4) 秦淮河","url":"https://podcasts.rthk.hk/podcast/media/taleoftheland/1622_2005071445_73369.mp3"}]},{"broadcast_date":"2020-05-16","title":"#41 南京","episodes":1,"podcasts":[{"caption":"(5) 明孝陵","url":"https://podcasts.rthk.hk/podcast/media/taleoftheland/1622_2005141054_57929.mp3"}]},{"broadcast_date":"2020-05-23","title":"#42 南京","episodes":1,"podcasts":[{"caption":"(6) 靈谷寺與雞鳴寺\t","url":"https://podcasts.rthk.hk/podcast/media/taleoftheland/1622_2005141054_61579.mp3"}]},{"broadcast_date":"2020-05-30","title":"#43 南京","episodes":1,"podcasts":[{"caption":"(7) 栖霞山","url":"https://podcasts.rthk.hk/podcast/media/taleoftheland/1622_2008311619_31858.mp3"}]},{"broadcast_date":"2020-06-06","title":"#44 南京","episodes":1,"podcasts":[{"caption":"(8) 火燒功臣樓","url":"https://podcasts.rthk.hk/podcast/media/taleoftheland/1622_2008311619_10010.mp3"}]},{"broadcast_date":"2020-06-13","title":"#45 南京","episodes":1,"podcasts":[{"caption":"(9) 繡球山","url":"https://podcasts.rthk.hk/podcast/media/taleoftheland/1622_2006091632_33162.mp3"}]},{"broadcast_date":"2020-06-20","title":"#46 南京","episodes":1,"podcasts":[{"caption":"(10) 狀元境與顧樓街","url":"https://podcasts.rthk.hk/podcast/media/taleoftheland/1622_2006091632_73603.mp3"}]},{"broadcast_date":"2020-06-27","title":"#47 太湖","episodes":1,"podcasts":[{"caption":"(1) 無錫 (上)","url":"https://podcasts.rthk.hk/podcast/media/taleoftheland/1622_2007091033_49823.mp3"}]},{"broadcast_date":"2020-07-04","title":"#48 太湖","episodes":1,"podcasts":[{"caption":"(2) 無錫 (下)","url":"https://podcasts.rthk.hk/podcast/media/taleoftheland/1622_2007091033_53920.mp3"}]},{"broadcast_date":"2020-07-11","title":"#49 太湖","episodes":1,"podcasts":[{"caption":"(3) 惠山泥人","url":"https://podcasts.rthk.hk/podcast/media/taleoftheland/1622_2007091033_82055.mp3"}]},{"broadcast_date":"2020-07-18","title":"#50 太湖","episodes":1,"podcasts":[{"caption":"(4) 惠山寺","url":"https://podcasts.rthk.hk/podcast/media/taleoftheland/1622_2007091033_60073.mp3"}]},{"broadcast_date":"2020-08-29","title":"#51 太湖","episodes":1,"podcasts":[{"caption":"(5) 寄暢園","url":"https://podcasts.rthk.hk/podcast/media/taleoftheland/1622_2008281829_87567.mp3"}]},{"broadcast_date":"2020-09-05","title":"#52 太湖","episodes":1,"podcasts":[{"caption":"(6) 梅園","url":"https://podcasts.rthk.hk/podcast/media/taleoftheland/1622_2009081646_79101.mp3"}]},{"broadcast_date":"2020-09-12","title":"#53 太湖","episodes":1,"podcasts":[{"caption":"(7) 蘇州","url":"https://podcasts.rthk.hk/podcast/media/taleoftheland/1622_2009081638_87900.mp3"}]},{"broadcast_date":"2020-09-19","title":"#54 太湖","episodes":1,"podcasts":[{"caption":"(8) 蘇州園林","url":"https://podcasts.rthk.hk/podcast/media/taleoftheland/1622_2009081638_55806.mp3"}]},{"broadcast_date":"2020-09-26","title":"#55 太湖","episodes":1,"podcasts":[{"caption":"(9) 蘇州西園寺","url":"https://podcasts.rthk.hk/podcast/media/taleoftheland/1622_2009171758_83233.mp3"}]},{"broadcast_date":"2020-10-03","title":"#56 太湖","episodes":1,"podcasts":[{"caption":"(10) 寒山寺","url":"https://podcasts.rthk.hk/podcast/media/taleoftheland/1622_2009171758_95751.mp3"}]},{"broadcast_date":"2020-10-10","title":"#57 太湖","episodes":1,"podcasts":[{"caption":"(11) 姑嫂塔與七子山","url":"https://podcasts.rthk.hk/podcast/media/taleoftheland/1622_2010091015_50746.mp3"}]},{"broadcast_date":"2020-10-17","title":"#58 太湖","episodes":1,"podcasts":[{"caption":"(12) 虎丘探奇","url":"https://podcasts.rthk.hk/podcast/media/taleoftheland/1622_2010091015_53153.mp3"}]},{"broadcast_date":"2020-10-24","title":"#59 太湖","episodes":1,"podcasts":[{"caption":"(13) 孫武亭與賴債廟","url":"https://podcasts.rthk.hk/podcast/media/taleoftheland/1622_2010231949_65426.mp3"}]},{"broadcast_date":"2020-10-31","title":"#60 太湖","episodes":1,"podcasts":[{"caption":"(14) 靈岩山","url":"https://podcasts.rthk.hk/podcast/media/taleoftheland/1622_2010231949_28708.mp3"}]},{"broadcast_date":"2020-11-07","title":"#61 太湖","episodes":1,"podcasts":[{"caption":"(15) 天平山與鄧尉山","url":"https://podcasts.rthk.hk/podcast/media/taleoftheland/1622_2011071632_78413.mp3"}]},{"broadcast_date":"2020-11-14","title":"#62 太湖","episodes":1,"podcasts":[{"caption":"(16) 洞庭東山和西山","url":"https://podcasts.rthk.hk/podcast/media/taleoftheland/1622_2012141433_31172.mp3"}]},{"broadcast_date":"2020-11-21","title":"#63 五台山","episodes":1,"podcasts":[{"caption":"(1)","url":"https://podcasts.rthk.hk/podcast/media/taleoftheland/1622_2012141433_34048.mp3"}]},{"broadcast_date":"2020-11-28","title":"#64 五台山","episodes":1,"podcasts":[{"caption":"(2) 顯通寺","url":"https://podcasts.rthk.hk/podcast/media/taleoftheland/1622_2012141434_19292.mp3"}]},{"broadcast_date":"2020-12-05","title":"#65 五台山","episodes":1,"podcasts":[{"caption":"(3) 塔院寺與菩薩頂","url":"https://podcasts.rthk.hk/podcast/media/taleoftheland/1622_2012141434_60689.mp3"}]},{"broadcast_date":"2021-02-06","title":"#66 五台山","episodes":1,"podcasts":[{"caption":"(4) 殊像寺","url":"https://podcasts.rthk.hk/podcast/media/taleoftheland/1622_2102201600_71045.mp3"}]},{"broadcast_date":"2021-02-13","title":"#67 五台山","episodes":1,"podcasts":[{"caption":"(5) 鎮海寺與人皮鼓","url":"https://podcasts.rthk.hk/podcast/media/taleoftheland/1622_2102201601_65614.mp3"}]},{"broadcast_date":"2021-02-20","title":"#68 五台山","episodes":1,"podcasts":[{"caption":"(6) 壽寧寺","url":"https://podcasts.rthk.hk/podcast/media/taleoftheland/1622_2102201601_40489.mp3"}]},{"broadcast_date":"2021-02-27","title":"#69 五台山","episodes":1,"podcasts":[{"caption":"(7) 大小賢與金閣寺","url":"https://podcasts.rthk.hk/podcast/media/taleoftheland/1622_2103050924_16303.mp3"}]},{"broadcast_date":"2021-03-06","title":"#70 五台山","episodes":1,"podcasts":[{"caption":"(8) 五台山的名僧","url":"https://podcasts.rthk.hk/podcast/media/taleoftheland/1622_2103050924_37443.mp3"}]},{"broadcast_date":"2021-03-13","title":"#71 南嶽衡山","episodes":1,"podcasts":[{"caption":"(1)","url":"https://podcasts.rthk.hk/podcast/media/taleoftheland/1622_2103241739_87220.mp3"}]},{"broadcast_date":"2021-03-20","title":"#72 南嶽衡山","episodes":1,"podcasts":[{"caption":"(2)","url":"https://podcasts.rthk.hk/podcast/media/taleoftheland/1622_2103241740_75344.mp3"}]},{"broadcast_date":"2021-03-27","title":"#73 南嶽衡山","episodes":1,"podcasts":[{"caption":"(3) 虎跑泉與磨鏡台","url":"https://podcasts.rthk.hk/podcast/media/taleoftheland/1622_2103241740_80976.mp3"}]},{"broadcast_date":"2021-04-03","title":"#74 南嶽衡山","episodes":1,"podcasts":[{"caption":"(4) 會仙橋","url":"https://podcasts.rthk.hk/podcast/media/taleoftheland/1622_2103241740_17172.mp3"}]},{"broadcast_date":"2021-04-10","title":"#75 南嶽衡山","episodes":1,"podcasts":[{"caption":"(5) 珍禽異獸","url":"https://podcasts.rthk.hk/podcast/media/taleoftheland/1622_2104081421_85070.mp3"}]},{"broadcast_date":"2021-04-17","title":"#76 南嶽衡山","episodes":1,"podcasts":[{"caption":"(6) 黃庭觀","url":"https://podcasts.rthk.hk/podcast/media/taleoftheland/1622_2104131838_28787.mp3"}]},{"broadcast_date":"2021-04-24","title":"#77 黃山","episodes":1,"podcasts":[{"caption":"(1) 黃帝與黃山","url":"https://podcasts.rthk.hk/podcast/media/taleoftheland/1622_2104222127_83499.mp3"}]},{"broadcast_date":"2021-05-01","title":"#78 黃山","episodes":1,"podcasts":[{"caption":"(2) 黃山奇石","url":"https://podcasts.rthk.hk/podcast/media/taleoftheland/1622_2104222128_37498.mp3"}]},{"broadcast_date":"2021-05-08","title":"#79 黃山","episodes":1,"podcasts":[{"caption":"(3) 金雞叫天門","url":"https://podcasts.rthk.hk/podcast/media/taleoftheland/1622_2105051459_15422.mp3"}]},{"broadcast_date":"2021-05-15","title":"#80 黃山","episodes":1,"podcasts":[{"caption":"(4) 黃山猴子","url":"https://podcasts.rthk.hk/podcast/media/taleoftheland/1622_2105051501_30551.mp3"}]},{"broadcast_date":"2021-05-22","title":"#81 黃山","episodes":1,"podcasts":[{"caption":"(5) 人皮橋與萬年橋","url":"https://podcasts.rthk.hk/podcast/media/taleoftheland/1622_2106011123_74556.mp3"}]},{"broadcast_date":"2021-05-29","title":"#82 黃山","episodes":1,"podcasts":[{"caption":"(6) 慈光寺與普門","url":"https://podcasts.rthk.hk/podcast/media/taleoftheland/1622_2106011123_54107.mp3"}]},{"broadcast_date":"2021-06-05","title":"#83 黃山","episodes":1,"podcasts":[{"caption":"(7) 松谷庵與翠薇寺","url":"https://podcasts.rthk.hk/podcast/media/taleoftheland/1622_2106011123_92927.mp3"}]},{"broadcast_date":"2021-06-12","title":"#84 黃山","episodes":1,"podcasts":[{"caption":"(8) 李太白訪仙","url":"https://podcasts.rthk.hk/podcast/media/taleoftheland/1622_2106011123_90187.mp3"}]},{"broadcast_date":"2021-06-19","title":"#85 洛陽","episodes":1,"podcasts":[{"caption":"(1)","url":"https://podcasts.rthk.hk/podcast/media/taleoftheland/1622_2106160925_92771.mp3"}]},{"broadcast_date":"2021-06-26","title":"#86 洛陽","episodes":1,"podcasts":[{"caption":"(2) 白馬寺","url":"https://podcasts.rthk.hk/podcast/media/taleoftheland/1622_2106160925_69404.mp3"}]},{"broadcast_date":"2021-07-03","title":"#87 洛陽","episodes":1,"podcasts":[{"caption":"(3) 龍門石窟","url":"https://podcasts.rthk.hk/podcast/media/taleoftheland/1622_2107020913_69577.mp3"}]},{"broadcast_date":"2021-07-10","title":"#88 洛陽","episodes":1,"podcasts":[{"caption":"(4) 香山白居易 / 石人村","url":"https://podcasts.rthk.hk/podcast/media/taleoftheland/1622_2107061723_83093.mp3"}]},{"broadcast_date":"2021-07-17","title":"#89 洛陽","episodes":1,"podcasts":[{"caption":"(5) 牡丹花","url":"https://podcasts.rthk.hk/podcast/media/taleoftheland/1622_2107210935_25224.mp3"}]},{"broadcast_date":"2021-07-24","title":"#90 洛陽","episodes":1,"podcasts":[{"caption":"(6) 爛柯山","url":"https://podcasts.rthk.hk/podcast/media/taleoftheland/1622_2107210935_52847.mp3"}]},{"broadcast_date":"2021-07-31","title":"#91 洛陽","episodes":1,"podcasts":[{"caption":"(7) 金谷園","url":"https://podcasts.rthk.hk/podcast/media/taleoftheland/1622_2107301041_92402.mp3"}]},{"broadcast_date":"2021-08-07","title":"#92 洛陽","episodes":1,"podcasts":[{"caption":"(8) 邙山","url":"https://podcasts.rthk.hk/podcast/media/taleoftheland/1622_2108031507_20352.mp3"}]},{"broadcast_date":"2021-08-14","title":"#93 洛陽","episodes":1,"podcasts":[{"caption":"(9) 孔子問禮","url":"https://podcasts.rthk.hk/podcast/media/taleoftheland/1622_2108181125_12545.mp3"}]},{"broadcast_date":"2021-08-21","title":"#94 洛陽","episodes":1,"podcasts":[{"caption":"(10) 鐵門","url":"https://podcasts.rthk.hk/podcast/media/taleoftheland/1622_2108181125_27199.mp3"}]},{"broadcast_date":"2021-08-28","title":"#95 洛陽","episodes":1,"podcasts":[{"caption":"(11)","url":"https://podcasts.rthk.hk/podcast/media/taleoftheland/1622_2108261342_27149.mp3"}]},{"broadcast_date":"2021-09-04","title":"#96 桂林","episodes":1,"podcasts":[{"caption":"(1)","url":"https://podcasts.rthk.hk/podcast/media/taleoftheland/1622_2108261344_79689.mp3"}]},{"broadcast_date":"2021-09-11","title":"#97 桂林","episodes":1,"podcasts":[{"caption":"(2)","url":"https://podcasts.rthk.hk/podcast/media/taleoftheland/1622_2109091425_36421.mp3"}]},{"broadcast_date":"2021-09-18","title":"#98 桂林","episodes":1,"podcasts":[{"caption":"(3) 蘆笛岩","url":"https://podcasts.rthk.hk/podcast/media/taleoftheland/1622_2109171724_74318.mp3"}]},{"broadcast_date":"2021-09-25","title":"#99 桂林","episodes":1,"podcasts":[{"caption":"(4) 七星公園","url":"https://podcasts.rthk.hk/podcast/media/taleoftheland/1622_2109230850_55846.mp3"}]},{"broadcast_date":"2021-10-02","title":"#100 桂林","episodes":1,"podcasts":[{"caption":"(5) 七星岩和酒壺山","url":"https://podcasts.rthk.hk/podcast/media/taleoftheland/1622_2109291450_78312.mp3"}]},{"broadcast_date":"2021-10-16","title":"#101 桂林","episodes":1,"podcasts":[{"caption":"(6) 象鼻山","url":"https://podcasts.rthk.hk/podcast/media/taleoftheland/1622_2109291452_50732.mp3"}]},{"broadcast_date":"2021-10-23","title":"#102 桂林","episodes":1,"podcasts":[{"caption":"(7) 疊彩山","url":"https://podcasts.rthk.hk/podcast/media/taleoftheland/1622_2110131839_54029.mp3"}]},{"broadcast_date":"2021-10-30","title":"#103 桂林","episodes":1,"podcasts":[{"caption":"(8) 漓江 (一)","url":"https://podcasts.rthk.hk/podcast/media/taleoftheland/1622_2110211014_72236.mp3"}]},{"broadcast_date":"2021-11-06","title":"#104 桂林","episodes":1,"podcasts":[{"caption":"(9) 漓江 (二)","url":"https://podcasts.rthk.hk/podcast/media/taleoftheland/1622_2110281441_97621.mp3"}]},{"broadcast_date":"2021-11-13","title":"#105 桂林","episodes":1,"podcasts":[{"caption":"(10) 漓江 (三) 冠岩 / 仙人推磨","url":"https://podcasts.rthk.hk/podcast/media/taleoftheland/1622_2111110933_43076.mp3"}]},{"broadcast_date":"2021-11-20","title":"#106 桂林","episodes":1,"podcasts":[{"caption":"(11) 漓江 (四) 盧山與美女梳妝","url":"https://podcasts.rthk.hk/podcast/media/taleoftheland/1622_2111192115_64554.mp3"}]},{"broadcast_date":"2021-11-27","title":"#107 桂林","episodes":1,"podcasts":[{"caption":"(12) 南溪山","url":"https://podcasts.rthk.hk/podcast/media/taleoftheland/1622_2111241727_53556.mp3"}]},{"broadcast_date":"2021-12-04","title":"#108 桂林","episodes":1,"podcasts":[{"caption":"(13) 隱山與西山","url":"https://podcasts.rthk.hk/podcast/media/taleoftheland/1622_2111241727_75610.mp3"}]},{"broadcast_date":"2021-12-11","title":"#109 桂林","episodes":1,"podcasts":[{"caption":"(14) 伏波山","url":"https://podcasts.rthk.hk/podcast/media/taleoftheland/1622_2111241728_17641.mp3"}]},{"broadcast_date":"2021-12-18","title":"#110 桂林","episodes":1,"podcasts":[{"caption":"(15) 穿山與堯山","url":"https://podcasts.rthk.hk/podcast/media/taleoftheland/1622_2112171737_32218.mp3"}]},{"broadcast_date":"2021-12-25","title":"#111 桂林","episodes":1,"podcasts":[{"caption":"(16) 陽朔 (一)","url":"https://podcasts.rthk.hk/podcast/media/taleoftheland/1622_2112171737_66081.mp3"}]},{"broadcast_date":"2022-01-01","title":"#112 桂林","episodes":1,"podcasts":[{"caption":"(17) 陽朔 (二)","url":"https://podcasts.rthk.hk/podcast/media/taleoftheland/1622_2201011346_52112.mp3"}]},{"broadcast_date":"2022-01-15","title":"#113 桂林","episodes":1,"podcasts":[{"caption":"(18) 靈渠","url":"https://podcasts.rthk.hk/podcast/media/taleoftheland/1622_2201041629_99347.mp3"}]},{"broadcast_date":"2022-01-22","title":"#114 北京","episodes":1,"podcasts":[{"caption":"(1)","url":"https://podcasts.rthk.hk/podcast/media/taleoftheland/1622_2201171302_91408.mp3"}]},{"broadcast_date":"2022-01-29","title":"#115 北京","episodes":1,"podcasts":[{"caption":"(2)","url":"https://podcasts.rthk.hk/podcast/media/taleoftheland/1622_2201171302_21509.mp3"}]},{"broadcast_date":"2022-02-05","title":"#116 北京","episodes":1,"podcasts":[{"caption":"(3) 紫禁城","url":"https://podcasts.rthk.hk/podcast/media/taleoftheland/1622_2201261137_22609.mp3"}]},{"broadcast_date":"2022-02-12","title":"#117 北京","episodes":1,"podcasts":[{"caption":"(4) 冷宮","url":"https://podcasts.rthk.hk/podcast/media/taleoftheland/1622_2202221047_63647.mp3"}]},{"broadcast_date":"2022-02-19","title":"#118 北京","episodes":1,"podcasts":[{"caption":"(5) 阿丑的故事","url":"https://podcasts.rthk.hk/podcast/media/taleoftheland/1622_2202221048_20817.mp3"}]},{"broadcast_date":"2022-02-26","title":"#119 北京","episodes":1,"podcasts":[{"caption":"(6) 壬寅宮變","url":"https://podcasts.rthk.hk/podcast/media/taleoftheland/1622_2202221048_81833.mp3"}]},{"broadcast_date":"2022-03-05","title":"#120 北京","episodes":1,"podcasts":[{"caption":"(7) 鑄鐘娘娘的故事","url":"https://podcasts.rthk.hk/podcast/media/taleoftheland/1622_2203051128_83102.mp3"}]},{"broadcast_date":"2022-03-12","title":"#121 北京","episodes":1,"podcasts":[{"caption":"(8) 頤和園","url":"https://podcasts.rthk.hk/podcast/media/taleoftheland/1622_2203051132_47387.mp3"}]},{"broadcast_date":"2022-03-19","title":"#122 北京","episodes":1,"podcasts":[{"caption":"(9) 頤和園與慈禧太后","url":"https://podcasts.rthk.hk/podcast/media/taleoftheland/1622_2203051132_39520.mp3"}]},{"broadcast_date":"2022-03-26","title":"#123 北京","episodes":1,"podcasts":[{"caption":"(10) 敗家石與蘇州街","url":"https://podcasts.rthk.hk/podcast/media/taleoftheland/1622_2203241429_95455.mp3"}]},{"broadcast_date":"2022-04-02","title":"#124 北京","episodes":1,"podcasts":[{"caption":"(11) 明十三陵","url":"https://podcasts.rthk.hk/podcast/media/taleoftheland/1622_2204081609_48532.mp3"}]},{"broadcast_date":"2022-04-09","title":"#125 北京","episodes":1,"podcasts":[{"caption":"(12) 十三陵的石人石獸","url":"https://podcasts.rthk.hk/podcast/media/taleoftheland/1622_2204081609_27131.mp3"}]},{"broadcast_date":"2022-04-16","title":"#126 北京","episodes":1,"podcasts":[{"caption":"(13) 萬里長城","url":"https://podcasts.rthk.hk/podcast/media/taleoftheland/1622_2204131918_75926.mp3"}]},{"broadcast_date":"2022-04-23","title":"#127 北京","episodes":1,"podcasts":[{"caption":"(14) 望京石","url":"https://podcasts.rthk.hk/podcast/media/taleoftheland/1622_2204131918_55223.mp3"}]},{"broadcast_date":"2022-04-30","title":"#128 北京","episodes":1,"podcasts":[{"caption":"(15) 潭柘寺","url":"https://podcasts.rthk.hk/podcast/media/taleoftheland/1622_2205301109_23371.mp3"}]},{"broadcast_date":"2022-05-07","title":"#129 北京","episodes":1,"podcasts":[{"caption":"(16) 白雲觀與天寧寺","url":"https://podcasts.rthk.hk/podcast/media/taleoftheland/1622_2205301107_83915.mp3"}]},{"broadcast_date":"2022-05-14","title":"#130 西安","episodes":1,"podcasts":[{"caption":"(1) 大雁塔與小雁塔","url":"https://podcasts.rthk.hk/podcast/media/taleoftheland/1622_2205301107_17585.mp3"}]},{"broadcast_date":"2022-05-21","title":"#131 西安","episodes":1,"podcasts":[{"caption":"(2) 鐘樓與鼓樓","url":"https://podcasts.rthk.hk/podcast/media/taleoftheland/1622_2205301108_69893.mp3"}]},{"broadcast_date":"2022-05-28","title":"#132 西安","episodes":1,"podcasts":[{"caption":"(3) 樓觀台","url":"https://podcasts.rthk.hk/podcast/media/taleoftheland/1622_2205301108_71505.mp3"}]},{"broadcast_date":"2022-06-04","title":"#133 西安","episodes":1,"podcasts":[{"caption":"(4) 咸陽古渡與鴻門宴故址","url":"https://podcasts.rthk.hk/podcast/media/taleoftheland/1622_2205311821_68512.mp3"}]},{"broadcast_date":"2022-06-11","title":"#134 西安","episodes":1,"podcasts":[{"caption":"(5) 茂陵","url":"https://podcasts.rthk.hk/podcast/media/taleoftheland/1622_2206100953_70184.mp3"}]},{"broadcast_date":"2022-06-18","title":"#135 西安","episodes":1,"podcasts":[{"caption":"(6) 昭陵","url":"https://podcasts.rthk.hk/podcast/media/taleoftheland/1622_2206100954_84497.mp3"}]}],"years":[{"name":"2019","podcasts":[{"title":"#1 廬山","episodes":1},{"title":"#2 廬山","episodes":1},{"title":"#3 廬山","episodes":1},{"title":"#4 廬山","episodes":1},{"title":"#5 廬山","episodes":1},{"title":"#06 廬山","episodes":1},{"title":"#07 廬山","episodes":1},{"title":"#08 廬山","episodes":1},{"title":"#9 長江三峽","episodes":1},{"title":"#10 長江三峽","episodes":1},{"title":"#11 長江三峽","episodes":1},{"title":"#12 長江三峽","episodes":1},{"title":"#13 長江三峽","episodes":1},{"title":"#14 長江三峽","episodes":1},{"title":"#15 長江三峽","episodes":1},{"title":"長江三峽","episodes":1},{"title":"#17 長江三峽","episodes":1},{"title":"#18 長江三峽","episodes":1},{"title":"#19 長江三峽","episodes":1},{"title":"#20 長江三峽","episodes":1},{"title":"#21 長江三峽","episodes":1}]},{"name":"2020","podcasts":[{"title":"#22 長江三峽","episodes":1},{"title":"#23 杭州","episodes":1},{"title":"#24 杭州","episodes":1},{"title":"#25 杭州","episodes":1},{"title":"#26 杭州","episodes":1},{"title":"#27 杭州","episodes":1},{"title":"#28 杭州","episodes":1},{"title":"#29 杭州","episodes":1},{"title":"#30 杭州","episodes":1},{"title":"#31 杭州","episodes":1},{"title":"#32 杭州","episodes":1},{"title":"#33 杭州","episodes":1},{"title":"#34 杭州","episodes":1},{"title":"#35 杭州","episodes":1},{"title":"#36 杭州","episodes":1},{"title":"#37 南京","episodes":1},{"title":"#38 南京","episodes":1},{"title":"#39 南京","episodes":1},{"title":"#40 南京","episodes":1},{"title":"#41 南京","episodes":1},{"title":"#42 南京","episodes":1},{"title":"#43 南京","episodes":1},{"title":"#44 南京","episodes":1},{"title":"#45 南京","episodes":1},{"title":"#46 南京","episodes":1},{"title":"#47 太湖","episodes":1},{"title":"#48 太湖","episodes":1},{"title":"#49 太湖","episodes":1},{"title":"#50 太湖","episodes":1},{"title":"#51 太湖","episodes":1},{"title":"#52 太湖","episodes":1},{"title":"#53 太湖","episodes":1},{"title":"#54 太湖","episodes":1},{"title":"#55 太湖","episodes":1},{"title":"#56 太湖","episodes":1},{"title":"#57 太湖","episodes":1},{"title":"#58 太湖","episodes":1},{"title":"#59 太湖","episodes":1},{"title":"#60 太湖","episodes":1},{"title":"#61 太湖","episodes":1},{"title":"#62 太湖","episodes":1},{"title":"#63 五台山","episodes":1},{"title":"#64 五台山","episodes":1},{"title":"#65 五台山","episodes":1}]},{"name":"2021","podcasts":[{"title":"#66 五台山","episodes":1},{"title":"#67 五台山","episodes":1},{"title":"#68 五台山","episodes":1},{"title":"#69 五台山","episodes":1},{"title":"#70 五台山","episodes":1},{"title":"#71 南嶽衡山","episodes":1},{"title":"#72 南嶽衡山","episodes":1},{"title":"#73 南嶽衡山","episodes":1},{"title":"#74 南嶽衡山","episodes":1},{"title":"#75 南嶽衡山","episodes":1},{"title":"#76 南嶽衡山","episodes":1},{"title":"#77 黃山","episodes":1},{"title":"#78 黃山","episodes":1},{"title":"#79 黃山","episodes":1},{"title":"#80 黃山","episodes":1},{"title":"#81 黃山","episodes":1},{"title":"#82 黃山","episodes":1},{"title":"#83 黃山","episodes":1},{"title":"#84 黃山","episodes":1},{"title":"#85 洛陽","episodes":1},{"title":"#86 洛陽","episodes":1},{"title":"#87 洛陽","episodes":1},{"title":"#88 洛陽","episodes":1},{"title":"#89 洛陽","episodes":1},{"title":"#90 洛陽","episodes":1},{"title":"#91 洛陽","episodes":1},{"title":"#92 洛陽","episodes":1},{"title":"#93 洛陽","episodes":1},{"title":"#94 洛陽","episodes":1},{"title":"#95 洛陽","episodes":1},{"title":"#96 桂林","episodes":1},{"title":"#97 桂林","episodes":1},{"title":"#98 桂林","episodes":1},{"title":"#99 桂林","episodes":1},{"title":"#100 桂林","episodes":1},{"title":"#101 桂林","episodes":1},{"title":"#102 桂林","episodes":1},{"title":"#103 桂林","episodes":1},{"title":"#104 桂林","episodes":1},{"title":"#105 桂林","episodes":1},{"title":"#106 桂林","episodes":1},{"title":"#107 桂林","episodes":1},{"title":"#108 桂林","episodes":1},{"title":"#109 桂林","episodes":1},{"title":"#110 桂林","episodes":1},{"title":"#111 桂林","episodes":1}]},{"name":"2022","podcasts":[{"title":"#112 桂林","episodes":1},{"title":"#113 桂林","episodes":1},{"title":"#114 北京","episodes":1},{"title":"#115 北京","episodes":1},{"title":"#116 北京","episodes":1},{"title":"#117 北京","episodes":1},{"title":"#118 北京","episodes":1},{"title":"#119 北京","episodes":1},{"title":"#120 北京","episodes":1},{"title":"#121 北京","episodes":1},{"title":"#122 北京","episodes":1},{"title":"#123 北京","episodes":1},{"title":"#124 北京","episodes":1},{"title":"#125 北京","episodes":1},{"title":"#126 北京","episodes":1},{"title":"#127 北京","episodes":1},{"title":"#128 北京","episodes":1},{"title":"#129 北京","episodes":1},{"title":"#130 西安","episodes":1},{"title":"#131 西安","episodes":1},{"title":"#132 西安","episodes":1},{"title":"#133 西安","episodes":1},{"title":"#134 西安","episodes":1},{"title":"#135 西安","episodes":1}]}]}